aiokdb/__init__.py
aiokdb/adapter.py
aiokdb/cli.py
aiokdb/client.py
aiokdb/compress.py
aiokdb/context.py
aiokdb/extras.py
aiokdb/files.py
aiokdb/format.py
aiokdb/py.typed
aiokdb/server.py
aiokdb/socket.py
aiokdb-0.1.34.dist-info/licenses/LICENSE
aiokdb-0.1.34.dist-info/METADATA
aiokdb-0.1.34.dist-info/WHEEL
aiokdb-0.1.34.dist-info/top_level.txt
aiokdb-0.1.34.dist-info/RECORD
