Metadata-Version: 2.4
Name: aiokdb
Version: 0.1.34
Summary: Pure Python asyncio connector to KDB
Author-email: Chris Shucksmith <chris@shucksmith.co.uk>
Project-URL: Homepage, https://github.com/TeaEngineering/aiokdb
Project-URL: Issues, https://github.com/TeaEngineering/aiokdb/issues
Classifier: Programming Language :: Python :: 3.8
Classifier: Programming Language :: Python :: 3.9
Classifier: Programming Language :: Python :: 3.10
Classifier: Programming Language :: Python :: 3.11
Classifier: Programming Language :: Python :: 3.12
Classifier: License :: OSI Approved :: MIT License
Classifier: Operating System :: OS Independent
Requires-Python: >=3.8
License-File: LICENSE
Dynamic: license-file
